.bumpversion.cfg
.editorconfig
.gitignore
.travis.yml
CONTRIBUTING.rst
HISTORY.rst
LICENSE
MANIFEST.in
Makefile
README.rst
conda-requirements.txt
pip-requirements.txt
poissonregime.py
requirements_dev.txt
setup.cfg
setup.py
docs/Makefile
docs/conf.py
docs/contributing.rst
docs/gamma_limits_sensitivity.rst
docs/history.rst
docs/index.rst
docs/issues.rst
docs/make.bat
docs/modules.rst
docs/poissonregime.rst
docs/static/icon.ico
docs/static/logo.png
gamma_limits_sensitivity/.gitignore
gamma_limits_sensitivity/.travis.yml
gamma_limits_sensitivity/__init__.py
gamma_limits_sensitivity/__main__.py
gamma_limits_sensitivity/resources/A_eff/AeffEnergy_P8R2_OnAxis_Total.dat
gamma_limits_sensitivity/resources/A_eff/MAGIC_lowZd_Ecut_300GeV.dat
gamma_limits_sensitivity/resources/A_eff/MAGIC_medZd_Ecut_300GeV.dat
gamma_limits_sensitivity/resources/A_eff/VERITAS_V5_lowZd_McCutcheon.dat
gamma_limits_sensitivity/resources/A_eff/uhe_test_aperture.dat
poissonregime.egg-info/PKG-INFO
poissonregime.egg-info/SOURCES.txt
poissonregime.egg-info/dependency_links.txt
poissonregime.egg-info/requires.txt
poissonregime.egg-info/top_level.txt
tests/bb.py
tests/helper_functions_for_tests.py
tests/test_command_predict.py
tests/test_command_sens.py
tests/test_command_ul.py
tests/test_core_functions.py
tests/test_effective_area.py
tests/test_funcs.py
tests/test_high_level_api.py
tests/yellin/__init__.py