Metadata-Version: 1.2
Name: poissonregime
Version: 0.1.0
Summary: Poisson error bars for low count statistics, detection significances.
Home-page: https://github.com/JohannesBuchner/poissonregime
Author: Johannes Buchner
Author-email: johannes.buchner.acad@gmx.com
License: MIT
Keywords: poissonregime
Platform: UNKNOWN
Classifier: Development Status :: 2 - Pre-Alpha
Classifier: Intended Audience :: Developers
Classifier: License :: OSI Approved :: GNU General Public License v3 (GPLv3)
Classifier: Natural Language :: English
Classifier: Programming Language :: Python :: 2
Classifier: Programming Language :: Python :: 2.7
Classifier: Programming Language :: Python :: 3
Classifier: Programming Language :: Python :: 3.5
Classifier: Programming Language :: Python :: 3.6
Classifier: Programming Language :: Python :: 3.7
Requires-Python: >=2.7, !=3.0.*, !=3.1.*, !=3.2.*, !=3.3.*, !=3.4.*
